LICENSE.txt
MANIFEST.in
README.md
setup.cfg
setup.py
labbook/__init__.py
labbook/mypackage.py
labbook.egg-info/PKG-INFO
labbook.egg-info/SOURCES.txt
labbook.egg-info/dependency_links.txt
labbook.egg-info/top_level.txt
labbook.egg-info/zip-safe
test/test_mypackage.py