Metadata-Version: 1.1
Name: labbook
Version: 1.0.0.2
Summary: Python package to work with labbook
Home-page: http://pypi.python.org/pypi/labbook
Author: Harsha Krishnareddy
Author-email: c0mpiler@outlook.com
License: MIT
Download-URL: http://pypi.python.org/pypi/labbook
Keywords: template,labbook,empty,package,example
Platform: Independant
Classifier: License :: OSI Approved :: BSD License
Classifier: Programming Language :: Python :: 2
Classifier: Programming Language :: Python :: 3
Classifier: Intended Audience :: Developers
Classifier: Topic :: Software Development :: Libraries :: Python Modules
